ydk_models_cisco_ios_xe-16.8.1.post1-nspkg.pth
ydk/models/cisco_ios_xe/ATM_FORUM_TC_MIB.py
ydk/models/cisco_ios_xe/ATM_MIB.py
ydk/models/cisco_ios_xe/ATM_TC_MIB.py
ydk/models/cisco_ios_xe/BGP4_MIB.py
ydk/models/cisco_ios_xe/BRIDGE_MIB.py
ydk/models/cisco_ios_xe/CISCO_AAA_SERVER_MIB.py
ydk/models/cisco_ios_xe/CISCO_AAA_SESSION_MIB.py
ydk/models/cisco_ios_xe/CISCO_ATM_EXT_MIB.py
ydk/models/cisco_ios_xe/CISCO_ATM_PVCTRAP_EXTN_MIB.py
ydk/models/cisco_ios_xe/CISCO_ATM_QOS_MIB.py
ydk/models/cisco_ios_xe/CISCO_BGP4_MIB.py
ydk/models/cisco_ios_xe/CISCO_BGP_POLICY_ACCOUNTING_MIB.py
ydk/models/cisco_ios_xe/CISCO_BULK_FILE_MIB.py
ydk/models/cisco_ios_xe/CISCO_CBP_TARGET_MIB.py
ydk/models/cisco_ios_xe/CISCO_CBP_TARGET_TC_MIB.py
ydk/models/cisco_ios_xe/CISCO_CBP_TC_MIB.py
ydk/models/cisco_ios_xe/CISCO_CDP_MIB.py
ydk/models/cisco_ios_xe/CISCO_CEF_MIB.py
ydk/models/cisco_ios_xe/CISCO_CEF_TC.py
ydk/models/cisco_ios_xe/CISCO_CONFIG_COPY_MIB.py
ydk/models/cisco_ios_xe/CISCO_CONFIG_MAN_MIB.py
ydk/models/cisco_ios_xe/CISCO_CONTEXT_MAPPING_MIB.py
ydk/models/cisco_ios_xe/CISCO_DATA_COLLECTION_MIB.py
ydk/models/cisco_ios_xe/CISCO_DIAL_CONTROL_MIB.py
ydk/models/cisco_ios_xe/CISCO_DOT3_OAM_MIB.py
ydk/models/cisco_ios_xe/CISCO_DYNAMIC_TEMPLATE_MIB.py
ydk/models/cisco_ios_xe/CISCO_DYNAMIC_TEMPLATE_TC_MIB.py
ydk/models/cisco_ios_xe/CISCO_EIGRP_MIB.py
ydk/models/cisco_ios_xe/CISCO_EMBEDDED_EVENT_MGR_MIB.py
ydk/models/cisco_ios_xe/CISCO_ENHANCED_MEMPOOL_MIB.py
ydk/models/cisco_ios_xe/CISCO_ENTITY_ALARM_MIB.py
ydk/models/cisco_ios_xe/CISCO_ENTITY_EXT_MIB.py
ydk/models/cisco_ios_xe/CISCO_ENTITY_FRU_CONTROL_MIB.py
ydk/models/cisco_ios_xe/CISCO_ENTITY_QFP_MIB.py
ydk/models/cisco_ios_xe/CISCO_ENTITY_SENSOR_MIB.py
ydk/models/cisco_ios_xe/CISCO_ENVMON_MIB.py
ydk/models/cisco_ios_xe/CISCO_ETHERLIKE_EXT_MIB.py
ydk/models/cisco_ios_xe/CISCO_ETHER_CFM_MIB.py
ydk/models/cisco_ios_xe/CISCO_FIREWALL_TC.py
ydk/models/cisco_ios_xe/CISCO_FLASH_MIB.py
ydk_models_cisco_ios_xe-16.8.1.post1.dist-info/DESCRIPTION.rst
ydk_models_cisco_ios_xe-16.8.1.post1.dist-info/METADATA
ydk_models_cisco_ios_xe-16.8.1.post1.dist-info/RECORD
ydk_models_cisco_ios_xe-16.8.1.post1.dist-info/WHEEL
ydk_models_cisco_ios_xe-16.8.1.post1.dist-info/metadata.json
ydk_models_cisco_ios_xe-16.8.1.post1.dist-info/namespace_packages.txt
ydk_models_cisco_ios_xe-16.8.1.post1.dist-info/top_level.txt
